setup.py
distributions_mbm/Binomialdistribution.py
distributions_mbm/Gaussiandistribution.py
distributions_mbm/Generaldistribution.py
distributions_mbm/__init__.py
distributions_mbm.egg-info/PKG-INFO
distributions_mbm.egg-info/SOURCES.txt
distributions_mbm.egg-info/dependency_links.txt
distributions_mbm.egg-info/not-zip-safe
distributions_mbm.egg-info/top_level.txt